{
    "image": "35.png",
    "regions": [
        {
            "page": "35",
            "chapter": 2.0,
            "verse": 220,
            "color": "blue",
            "bbox": {
                "x": 64,
                "y": 130,
                "width": 814,
                "height": 84
            }
        },
        {
            "page": "35",
            "chapter": 2.0,
            "verse": 220,
            "color": "blue",
            "bbox": {
                "x": 64,
                "y": 215,
                "width": 814,
                "height": 85
            }
        },
        {
            "page": "35",
            "chapter": 2.0,
            "verse": 220,
            "color": "blue",
            "bbox": {
                "x": 120,
                "y": 301,
                "width": 758,
                "height": 85
            }
        },
        {
            "page": "35",
            "chapter": 2.0,
            "verse": 221,
            "color": "red",
            "bbox": {
                "x": 64,
                "y": 387,
                "width": 814,
                "height": 85
            }
        },
        {
            "page": "35",
            "chapter": 2.0,
            "verse": 221,
            "color": "red",
            "bbox": {
                "x": 64,
                "y": 473,
                "width": 814,
                "height": 85
            }
        },
        {
            "page": "35",
            "chapter": 2.0,
            "verse": 221,
            "color": "red",
            "bbox": {
                "x": 64,
                "y": 559,
                "width": 814,
                "height": 85
            }
        },
        {
            "page": "35",
            "chapter": 2.0,
            "verse": 221,
            "color": "red",
            "bbox": {
                "x": 64,
                "y": 645,
                "width": 814,
                "height": 85
            }
        },
        {
            "page": "35",
            "chapter": 2.0,
            "verse": 221,
            "color": "red",
            "bbox": {
                "x": 120,
                "y": 731,
                "width": 758,
                "height": 85
            }
        },
        {
            "page": "35",
            "chapter": 2.0,
            "verse": 222,
            "color": "blue",
            "bbox": {
                "x": 64,
                "y": 817,
                "width": 814,
                "height": 85
            }
        },
        {
            "page": "35",
            "chapter": 2.0,
            "verse": 222,
            "color": "blue",
            "bbox": {
                "x": 64,
                "y": 903,
                "width": 814,
                "height": 85
            }
        },
        {
            "page": "35",
            "chapter": 2.0,
            "verse": 222,
            "color": "blue",
            "bbox": {
                "x": 118,
                "y": 989,
                "width": 760,
                "height": 85
            }
        },
        {
            "page": "35",
            "chapter": 2.0,
            "verse": 223,
            "color": "red",
            "bbox": {
                "x": 64,
                "y": 1075,
                "width": 814,
                "height": 85
            }
        },
        {
            "page": "35",
            "chapter": 2.0,
            "verse": 223,
            "color": "red",
            "bbox": {
                "x": 64,
                "y": 1161,
                "width": 814,
                "height": 85
            }
        },
        {
            "page": "35",
            "chapter": 2.0,
            "verse": 223,
            "color": "red",
            "bbox": {
                "x": 714,
                "y": 1247,
                "width": 164,
                "height": 85
            }
        },
        {
            "page": "35",
            "chapter": 2.0,
            "verse": 224,
            "color": "blue",
            "bbox": {
                "x": 64,
                "y": 1247,
                "width": 609,
                "height": 85
            }
        },
        {
            "page": "35",
            "chapter": 2.0,
            "verse": 224,
            "color": "blue",
            "bbox": {
                "x": 120,
                "y": 1333,
                "width": 758,
                "height": 85
            }
        }
    ]
}