{
    "image": "496.png",
    "regions": [
        {
            "page": "496",
            "chapter": 44.0,
            "verse": 1,
            "color": "blue",
            "bbox": {
                "x": 802,
                "y": 301,
                "width": 78,
                "height": 85
            }
        },
        {
            "page": "496",
            "chapter": 44.0,
            "verse": 2,
            "color": "red",
            "bbox": {
                "x": 478,
                "y": 301,
                "width": 282,
                "height": 85
            }
        },
        {
            "page": "496",
            "chapter": 44.0,
            "verse": 3,
            "color": "blue",
            "bbox": {
                "x": 66,
                "y": 301,
                "width": 371,
                "height": 85
            }
        },
        {
            "page": "496",
            "chapter": 44.0,
            "verse": 3,
            "color": "blue",
            "bbox": {
                "x": 583,
                "y": 387,
                "width": 297,
                "height": 85
            }
        },
        {
            "page": "496",
            "chapter": 44.0,
            "verse": 4,
            "color": "red",
            "bbox": {
                "x": 182,
                "y": 387,
                "width": 360,
                "height": 85
            }
        },
        {
            "page": "496",
            "chapter": 44.0,
            "verse": 5,
            "color": "blue",
            "bbox": {
                "x": 66,
                "y": 387,
                "width": 74,
                "height": 85
            }
        },
        {
            "page": "496",
            "chapter": 44.0,
            "verse": 5,
            "color": "blue",
            "bbox": {
                "x": 468,
                "y": 473,
                "width": 412,
                "height": 85
            }
        },
        {
            "page": "496",
            "chapter": 44.0,
            "verse": 6,
            "color": "red",
            "bbox": {
                "x": 66,
                "y": 473,
                "width": 360,
                "height": 85
            }
        },
        {
            "page": "496",
            "chapter": 44.0,
            "verse": 6,
            "color": "red",
            "bbox": {
                "x": 643,
                "y": 559,
                "width": 237,
                "height": 85
            }
        },
        {
            "page": "496",
            "chapter": 44.0,
            "verse": 7,
            "color": "blue",
            "bbox": {
                "x": 66,
                "y": 559,
                "width": 535,
                "height": 85
            }
        },
        {
            "page": "496",
            "chapter": 44.0,
            "verse": 7,
            "color": "blue",
            "bbox": {
                "x": 583,
                "y": 645,
                "width": 297,
                "height": 85
            }
        },
        {
            "page": "496",
            "chapter": 44.0,
            "verse": 8,
            "color": "red",
            "bbox": {
                "x": 66,
                "y": 645,
                "width": 476,
                "height": 85
            }
        },
        {
            "page": "496",
            "chapter": 44.0,
            "verse": 8,
            "color": "red",
            "bbox": {
                "x": 500,
                "y": 731,
                "width": 380,
                "height": 85
            }
        },
        {
            "page": "496",
            "chapter": 44.0,
            "verse": 9,
            "color": "blue",
            "bbox": {
                "x": 123,
                "y": 731,
                "width": 336,
                "height": 85
            }
        },
        {
            "page": "496",
            "chapter": 44.0,
            "verse": 10,
            "color": "red",
            "bbox": {
                "x": 307,
                "y": 817,
                "width": 573,
                "height": 85
            }
        },
        {
            "page": "496",
            "chapter": 44.0,
            "verse": 11,
            "color": "blue",
            "bbox": {
                "x": 66,
                "y": 817,
                "width": 199,
                "height": 85
            }
        },
        {
            "page": "496",
            "chapter": 44.0,
            "verse": 11,
            "color": "blue",
            "bbox": {
                "x": 631,
                "y": 903,
                "width": 249,
                "height": 85
            }
        },
        {
            "page": "496",
            "chapter": 44.0,
            "verse": 12,
            "color": "red",
            "bbox": {
                "x": 123,
                "y": 903,
                "width": 466,
                "height": 85
            }
        },
        {
            "page": "496",
            "chapter": 44.0,
            "verse": 13,
            "color": "blue",
            "bbox": {
                "x": 232,
                "y": 989,
                "width": 648,
                "height": 85
            }
        },
        {
            "page": "496",
            "chapter": 44.0,
            "verse": 14,
            "color": "red",
            "bbox": {
                "x": 66,
                "y": 989,
                "width": 125,
                "height": 85
            }
        },
        {
            "page": "496",
            "chapter": 44.0,
            "verse": 14,
            "color": "red",
            "bbox": {
                "x": 524,
                "y": 1075,
                "width": 356,
                "height": 85
            }
        },
        {
            "page": "496",
            "chapter": 44.0,
            "verse": 15,
            "color": "blue",
            "bbox": {
                "x": 66,
                "y": 1075,
                "width": 416,
                "height": 85
            }
        },
        {
            "page": "496",
            "chapter": 44.0,
            "verse": 15,
            "color": "blue",
            "bbox": {
                "x": 741,
                "y": 1161,
                "width": 139,
                "height": 85
            }
        },
        {
            "page": "496",
            "chapter": 44.0,
            "verse": 16,
            "color": "red",
            "bbox": {
                "x": 123,
                "y": 1161,
                "width": 576,
                "height": 85
            }
        },
        {
            "page": "496",
            "chapter": 44.0,
            "verse": 17,
            "color": "blue",
            "bbox": {
                "x": 123,
                "y": 1247,
                "width": 757,
                "height": 85
            }
        },
        {
            "page": "496",
            "chapter": 44.0,
            "verse": 18,
            "color": "red",
            "bbox": {
                "x": 123,
                "y": 1333,
                "width": 757,
                "height": 85
            }
        }
    ]
}