{
  "id": null,
  "sura": 5,
  "aya": 12,
  "text": "<p> الْأَنْهَارُ فَمَنْ كَفَرَ بَعْدَ ذَلِكَ مِنْكُمْ فَقَدْ ضَلَّ سَوَاءَ السَّبِيلِ}. </p><p> [١٢]  {وَلَقَدْ أَخَذَ اللَّهُ مِيثَاقَ بَنِي إِسْرَائِيلَ وَبَعَثْنَا مِنْهُمُ اثْنَيْ عَشَرَ نَقِيبًا} من كلِّ سبطٍ نقيبًا، والنقيبُ: الضَّمينُ والأمين، وهو الذي ينقبُ عن الأمور، ويتعرَّفُها. </p><p> رُوي أن بني إسرائيل لما فرغوا من أمرِ فرعونَ، واستقرُّوا بمصرَ، أمرَ اللهُ موسى وقومَه بالخروجِ إلى أريحا من أرضِ الشامِ، وكان يسكنُها الكنعانيون الجبارون ومنهم (١) عوجُ بنُ عنق وأصحابُه، ونسبته لأم عناقَ بنتِ آدمَ عليه الصلاة والسلام، وكان طولُه ثلاثةَ آلافٍ وثلاثَ مئةٍ وثلاثةً وثلاثينَ وثلثَ ذِراع، وكان يَحْتَجِزُ بالسحابِ، ويشربُ منه، ويتناولُ الحوتَ من قَرارِ البحرِ فيشويهِ بعينِ الشمسِ يرفعُه إليها، ثم يأكلُه، وعاشَ ثلاثةَ آلافِ سنةٍ حتى أهلكَه الله على يدِ موسى عليه الصلاة والسلام، وذلك أنه قطع صخرةً على قدرِ عسكرِ موسى ليطرحَها عليهم، وكان العسكرُ فرسخًا في فرسخ، فبعثَ اللهُ الهدهدَ، فقوَّرَ الصخرةَ بمنقاره، فوقعتْ في عنقِه، فصرعَتْهُ، فوثب موسى عليه الصلاة والسلام، وكانت وثبتُهُ عشرةَ أذرعٍ، وطولُه مثلُ ذلك، وطولُ عصاته مثلُ ذلك، ولم يلحقْ إلا عرقوبَه، فضربَهُ فقتله، وتُركَ بموضعِه، وأردمَ عليه بالصخر والرمل (٢) ، فكانَ كالجبلِ العظيمِ في صحراءِ مصرَ، ولما أمرَ اللهُ بني إسرائيلَ بالخروج إلى أريحا، قال لهم: إنِّي كتبتُها لكم دارَ قرارٍ، فاخرجوا إليها، وجاهدوا </p><p>(١) \"ومنهم\" زيادة من \"ظ\". (٢) في \"ظ\": \"بالرمل والصخر\".</p><p> مَنْ فيها؛ فإني ناصرُكم عليهم (١) ، واتخذَ موسى من قومِهِ اثني عشرَ نقيبًا، فعاهدَهُم أن يكفلوا بقومِهم، ولا يحدِّثوهم بما يرونَ من الجبارين، فلما رأوهم وما هم عليه من عِظَمِ الأجسادِ، نقضوا العهدَ، وحدثوهم، إلا كالبَ بنَ يوقنا من سبطِ يَهوذا ختنَ موسى على أختِهِ مريمَ بنتِ عمران، ويوشعَ بنَ نون من سبطِ أَفراييمَ بنِ يوسفَ فتى موسى، وأما أسماءُ العشرةِ الذين نقضوا العهدَ من النقباء، فهم شموعُ بنُ زكور من سبطِ روبين (٢) ، وشافاطُ (٣) بن حوري من سبطِ شمعون، ويغال بنُ يوسفَ من سبطِ يساخر، وبلطي بن رافوا من سبطِ بنيامين، وكدي بن سودي من سبطِ زبولون، وكدي بن سوسي من سبط منشا بنِ يوسفَ، وعميال بن كملي من سبط دان، وستورُ بن ميخائيل من سبطِ آشر، ونحبى بنُ وقسي من سبط نفتالي، وكوئيلُ بنُ ماخي من سبطِ كاد، فهؤلاء الذين دعا موسى عليهم، فهلكوا مسخوطًا عليهم (٤) . </p><p> {وَقَالَ اللَّهُ إِنِّي مَعَكُمْ} ناصرُكم على عدوِّكم. </p><p> {لَئِنْ أَقَمْتُمُ الصَّلَاةَ وَآتَيْتُمُ الزَّكَاةَ وَآمَنْتُمْ بِرُسُلِي وَعَزَّرْتُمُوهُمْ} عَظَّمتموهم. </p><p> {وَأَقْرَضْتُمُ اللَّهَ قَرْضًا حَسَنًا} بالإِنفاقِ في سبيل الخيرِ. </p><p> {لَأُكَفِّرَنَّ عَنْكُمْ} أي: لأمحوَنَّ عنكمُ. </p><p>(١) \"عليهم\" زيادة من \"ظ\". (٢) في \"ظ\": \"روبيل\".(٣) في \"ش\": \"شافط\".(٤) انظر: \"تفسير الطبري\" (٦/ ١٧٤)، و\"تفسير البغوي\" (١/ ٦٥٠)، و\"تفسير ابن كثير\" (٢/ ٣٩).</p>"
}