{
  "id": null,
  "sura": 26,
  "aya": 222,
  "text": "<p> {هَلْ أُنَبِّئُكُمْ عَلَى مَنْ تَنَزَّلُ الشَّيَاطِينُ (٢٢١) }. </p><p> [٢٢١] ولما قال المشركون: إن الشيطان يلقي السمع (١) على محمد، نزل جواب قولهم:  {هَلْ أُنَبِّئُكُمْ عَلَى مَنْ تَنَزَّلُ الشَّيَاطِينُ} ؟ </p><p> ... </p><p> {تَنَزَّلُ عَلَى كُلِّ أَفَّاكٍ أَثِيمٍ (٢٢٢) }. </p><p> [٢٢٢] ثم بين فقال: {تَنَزَّلُ} أي: تتنزل {عَلَى كُلِّ أَفَّاكٍ} كذاب. </p><p> {أَثِيمٍ} مبالغة من آثم، وهم الكهنة الذين كانت تسرق الجن السمع فتلقيه إليهم. قرأ البزي:  (تَّنزَّلُ) بتشديد التاء في الحرفين حالة الوصل (٢) . </p><p> ... </p><p> {يُلْقُونَ السَّمْعَ وَأَكْثَرُهُمْ كَاذِبُونَ (٢٢٣) }. </p><p> [٢٢٣]  {يُلْقُونَ السَّمْعَ} أي: يلقون إلى الكهنة ما يسمعون من الملائكة عند استراق السمع {وَأَكْثَرُهُمْ} أي: الكهنة. </p><p> {كَاذِبُونَ} لأنهم كانوا يخلطون مع ما يستمعون (٣) كذبًا كثيرًا. جاء في الحديث:  \"الكلمةُ يخطَفُها الجني، فَيَقُرُّها في أذن وليه، فيزيد فيها أكثر من مئة كذبة\"  (٤) . </p><p>(١) \"السمع\" زيادة من \"ت\". (٢) انظر: \"النشر في القراءات العشر\" لابن الجزري (٢/ ٢٣٢ - ٢٣٤)، و\"الغيث\" للصفاقسي (ص: ٣١٠)، و\"معجم القراءات القرآنية\" (٤/ ٣٣٠).(٣) في \"ش\": \"يسمعون\".(٤) رواه البخاري (٥٤٢٩)، كتاب: الطب، باب: الكهانة، ومسلم (٢٢٢٨) , كتاب: =</p>"
}