{
  "id": null,
  "sura": 75,
  "aya": 24,
  "text": "<p> {إِلَى رَبِّهَا نَاظِرَةٌ (٢٣) }. </p><p> [٢٣]  {إِلَى رَبِّهَا نَاظِرَةٌ} من نظر العين، وحمل هذه الآية جميعُ أهل السنة على أنها متضمنة رؤية المؤمنين لله تعالى بلا كيف ولا تحديد كما هو معلوم موجود، لا يشبه الموجودات، كذلك لا يشبه المرئيات في شيء، فإنه ليس كمثله شيء سبحانه. </p><p> قال - صلى الله عليه وسلم - \"إنكم ترون ربَّكم يومَ القيامة كما ترون القمرَ ليلةَ البدر لا تُضامون في رؤيته\"  (١) . </p><p> والمعتزلة ينفون رؤية الله تعالى، ويذهبون في هذه الآية إلى أن المعنى: إلى رحمة ربها ناظرة، وإلى ثوابه، أو إلى ملكه، فقدروا مضافًا محذوفًا، وتقدم الكلام على ذلك، واختلاف (٢) الأئمة على رؤيته سبحانه في الآخرة في سورة الأنعام. </p><p> ... </p><p> {وَوُجُوهٌ يَوْمَئِذٍ بَاسِرَةٌ (٢٤) }. </p><p> [٢٤]  {وَوُجُوهٌ يَوْمَئِذٍ بَاسِرَةٌ} عابسة متكرِّهة. </p><p> ... </p><p> {تَظُنُّ أَنْ يُفْعَلَ بِهَا فَاقِرَةٌ (٢٥) }. </p><p> [٢٥]  {تَظُنُّ} تتيقَّن {أَنْ يُفْعَلَ بِهَا فَاقِرَةٌ} داهية عظيمة تفقر؛ أي: تكسر فقار الظهر. </p><p>(١) رواه البخاري (٦٩٩٧)، كتاب: التوحيد، باب قوله تعالى: {وُجُوهٌ يَوْمَئِذٍ نَاضِرَةٌ}، ومسلم (٦٣٣)، كتاب، المساجد ومواضع الصلاة، باب: فضل صلاتي الصبح والعصر والمحافظة عليهما، من حديث جرير بن عبد الله رضي الله عنه. (٢) في \"ت\": \"اتفاق\".</p>"
}