{
  "id": null,
  "sura": 96,
  "aya": 1,
  "text": "<p> {اقْرَأْ بِاسْمِ رَبِّكَ الَّذِي خَلَقَ (١) }. </p><p> [١] ومعنى الآية: {اقْرَأْ} هذا القرآن مفتتحًا {بِاسْمِ رَبِّكَ} كما قال {وَقَالَ ارْكَبُوا فِيهَا بِسْمِ اللَّهِ مَجْرَاهَا}  [هود: ٤١] ، ودخلت الباء في بسم لتدل على الملازمة والتكرير، ولما ذكر الرب، وكانت العرب في الجاهلية تسمي الأصنام أربابًا، جاء بالصفة التي لا شركة للأصنام فيها، وهي قوله:  {الَّذِي خَلَقَ} . </p><p> ... </p><p> {خَلَقَ الْإِنْسَانَ مِنْ عَلَقٍ (٢) }. </p><p> [٢] ثم مثل لهم من المخلوقات ما لا مدافعة فيه، فقال:  {خَلَقَ الْإِنْسَانَ} أي: جنس الإنسان (١) إدريسُ عليه السلام. </p><p> {مِنْ عَلَقٍ} جمع علقة، وهي القطعة الصغيرة (٢) من الدم، وخلقةُ الإنسان من أعظم العبر، وليس المراد آدم عليه السلام؛ لأنه خُلق من طين. </p><p> ... </p><p> {اقْرَأْ وَرَبُّكَ الْأَكْرَمُ (٣) }. </p><p> [٣] ثم قال على جهة التأنيس: {اقْرَأْ وَرَبُّكَ الْأَكْرَمُ} الذي لا يلحقه نقص، فليس هو كهذه الأرباب، فهو ينصرك ويظهرك. </p><p> ... </p><p>(١) \"أي: جنس الإنسان\" زيادة من \"ت\". (٢) في \"ت\": \"اليسيرة\".</p>"
}